setup.py
eng2chs/eng2chs.py
eng2chs/getip.py
eng2chs/readip.py
eng2chs.egg-info/PKG-INFO
eng2chs.egg-info/SOURCES.txt
eng2chs.egg-info/dependency_links.txt
eng2chs.egg-info/requires.txt
eng2chs.egg-info/top_level.txt