Metadata-Version: 1.1
Name: eng2chs
Version: 0.10.7
Summary: a moudle used to translate english to chinese
Home-page: https://pypi.org/project/eng2chs/#description
Author: smvlboy
Author-email: smvlboy@outlook.com
License: UNKNOWN
Platform: UNKNOWN
Classifier: Environment :: Web Environment
Classifier: Programming Language :: Python
Classifier: Programming Language :: Python :: 3
